[
  {
    "category": "Foreigner Travel to China Helper",
    "product_name": "WeChat",
    "url": "https://www.wechat.com"
  },
  {
    "category": "Foreigner Travel to China Helper",
    "product_name": "Alipay",
    "url": "https://www.alipay.com"
  },
  {
    "category": "Foreigner Travel to China Helper",
    "product_name": "Trip.com",
    "url": "https://www.trip.com"
  },
  {
    "category": "Foreigner Travel to China Helper",
    "product_name": "DiDi",
    "url": "https://web.didiglobal.com"
  },
  {
    "category": "Foreigner Travel to China Helper",
    "product_name": "Amap (Gaode Maps)",
    "url": "https://mobile.amap.com"
  },
  {
    "category": "Foreigner Travel to China Helper",
    "product_name": "Pleco",
    "url": "https://www.pleco.com"
  },
  {
    "category": "Foreigner Travel to China Helper",
    "product_name": "Waygo",
    "url": "http://www.waygoapp.com"
  },
  {
    "category": "Foreigner Travel to China Helper",
    "product_name": "Baidu Maps",
    "url": "https://map.baidu.com"
  },
  {
    "category": "Foreigner Travel to China Helper",
    "product_name": "Meituan",
    "url": "https://www.meituan.com"
  },
  {
    "category": "Foreigner Travel to China Helper",
    "product_name": "China Railway 12306",
    "url": "https://www.12306.cn"
  }
]
