{
  "product_name": "Babbel",
  "url": "https://www.babbel.com",
  "download_url": null,
  "host_os": "darwin",
  "host_arch": "arm64",
  "runtime": "sandbox-local",
  "sandbox": {
    "image": "linux",
    "local": true,
    "mode": "local",
    "name": "analyzer-babbel-2026-05-19-2",
    "api_url": "http://localhost:53510"
  },
  "android": {
    "enabled": false,
    "apk_url": null,
    "apk_file": null,
    "package_name": null,
    "mode": null
  },
  "started_at": "2026-05-19T18:40:29+08:00",
  "finished_at": null,
  "mode": null,
  "last_session_id": "3ea67d11-6a70-4a93-b6d0-3a60aa3006f9",
  "screenshots": [],
  "warnings": []
}
